rtl/alu.sv
module alu (
    input logic [31:0] A, 
    input logic [31:0] B, 
    input logic [2:0] operation,
    output logic [31:0] result
); 
    always_comb 
        begin
            case(operation)
                3'b000: result = A + B; //ADD
                3'b001: result = A - B; //SUB
                3'b010: result = A & B; //AND
                3'b011: result = A | B; //OR
                3'b100: result = A ^ B; //XOR
                3'b101: result = A << B[4:0]; //SLL
                3'b110: result = A >> B[4:0]; //SRL
                3'b111: result = A == B; //Comparison
                default: result = 32'b0;
            endcase
        end 
endmodule

testbench/tb_alu.sv
module tb_alu;
    logic [31:0] A;
    logic [31:0] B;
    logic [2:0] operation;
    logic [31:0] result; 

    alu dut(
        .A(A),
        .B(B), 
        .operation(operation), 
        .result(result)
    ); 
    initial begin
        $dumpfile("alu_wave.vcd");
        $dumpvars(0, tb_alu);
        
        // Test Case 1: A = 3, B = 5, operation = 000 (Addition)
        A = 32'd3; 
        B = 32'd5; 
        operation = 3'b000; 
        #10; 
        if (result == 32'd8)
            $display("Test Case 1 Passed: Add %0d + %0d = %0d", A, B, result);
        else
            $error("Test Case 1 Failed: Add %0d + %0d, expected 8, got %0d", A, B, result);

         //Test Case 2: A = 3, B = 5, operation = 001 (Subtraction)
        A = 32'd3;
        B = 32'd5; 
        operation = 3'b001;
        #10;
        if (result == 32'd4294967294) // 3 - 5 = -2 in 32-bit unsigned is 4294967294
            $display("Test Case 2 Passed: Sub %0d - %0d = %0d", A, B, result);
        else
            $error("Test Case 2 Failed: Sub %0d - %0d, expected 4294967294, got %0d", A, B, result);
        
        //Test Case 3: A = 3, B = 5, operation = 010 (AND)
        A = 32'd3;
        B = 32'd5; 
        operation = 3'b010;
        #10;
        if (result == 32'd1) // 3 & 5 = 1
            $display("Test Case 3 Passed: AND %0d & %0d = %0d", A, B, result);
        else
            $error("Test Case 3 Failed: AND %0d & %0d, expected 1, got %0d", A, B, result);

         //Test Case 4: A = 3, B = 5, operation = 011 (OR)
        A = 32'd3;
        B = 32'd5; 
        operation = 3'b011;
        #10;
        if (result == 32'd7) // 3 | 5 = 7
            $display("Test Case 4 Passed: OR %0d | %0d = %0d", A, B, result);
        else 
            $error("Test Case 4 Failed: OR %0d | %0d, expected 7, got %0d", A, B, result); 

         //Test Case 5: A = 3, B = 5, operation = 100 (XOR)           
        A = 32'd3;
        B = 32'd5; 
        operation = 3'b100;
        #10;
        if (result == 32'd6) // 3 ^ 5 = 6
            $display("Test Case 5 Passed: XOR %0d ^ %0d = %0d", A, B, result); 
        else
            $error("Test Case 5 Failed: XOR %0d ^ %0d, expected 6, got %0d", A, B, result); 

         //Test Case 6: A = 3, B = 5, operation = 101 (SLL)
        A = 32'd3;
        B = 32'd5; 
        operation = 3'b101;
        #10;
        if (result == 32'd96) // 3 << 5 = 96
            $display("Test Case 6 Passed: SLL %0d << %0d = %0d", A, B, result);
        else
            $error("Test Case 6 Failed: SLL %0d << %0d, expected 96, got %0d", A, B, result);

         //Test Case 7: A = 3, B = 5, operation = 110 (SRL)
        A = 32'd3;
        B = 32'd5; 
        operation = 3'b110;
        #10;
        if (result == 32'd0) // 3 >> 5 = 0
            $display("Test Case 7 Passed: SRL %0d >> %0d = %0d", A, B, result);
        else
            $error("Test Case 7 Failed: SRL %0d >> %0d, expected 0, got %0d", A, B, result);

         //Test Case 8: A = 5, B = 5, operation = 111 (Comparison)
        A = 32'd5;
        B = 32'd5; 
        operation = 3'b111;
        #10;
        if (result == 32'd1) // 5 == 5 = 1
            $display("Test Case 8 Passed: Comparison %0d == %0d = %0d", A, B, result);
        else
            $error("Test Case 8 Failed: Comparison %0d == %0d, expected 1, got %0d", A, B, result);

        //Test Case 9: A = 1, B = 15, operation = 101 (SLL)
        A = 32'd1; 
        B = 32'd15; 
        operation = 3'b101;
        #10;
        if (result == 32'd32768) // 1 << 15 = 32768
            $display("Test Case 9 Passed: SLL %0d << %0d = %0d", A, B, result);
        else
            $error("Test Case 9 Failed: SLL %0d << %0d, expected 32768, got %0d", A, B, result);
    end
endmodule

alu_wave.vcd
$date
	Thu Aug 27 00:05:32 2026
$end
$version
	Icarus Verilog
$end
$timescale
	1s
$end
$scope module tb_alu $end
$var wire 32 ! result [31:0] $end
$var reg 32 " A [31:0] $end
$var reg 32 # B [31:0] $end
$var reg 3 $ operation [2:0] $end
$scope module dut $end
$var wire 32 % A [31:0] $end
$var wire 32 & B [31:0] $end
$var wire 3 ' operation [2:0] $end
$var reg 32 ( result [31:0] $end
$upscope $end
$upscope $end
$enddefinitions $end
$comment Show the parameter values. $end
$dumpall
$end
#0
$dumpvars
b1000 (
b0 '
b101 &
b11 %
b0 $
b101 #
b11 "
b1000 !
$end
#10
b11111111111111111111111111111110 !
b11111111111111111111111111111110 (
b1 $
b1 '
#20
b1 !
b1 (
b10 $
b10 '
#30
b111 !
b111 (
b11 $
b11 '
#40
b110 !
b110 (
b100 $
b100 '
#50
b1100000 !
b1100000 (
b101 $
b101 '
#60
b0 !
b0 (
b110 $
b110 '
#70
b1 !
b1 (
b111 $
b111 '
b101 "
b101 %
#80
b1000000000000000 !
b1000000000000000 (
b101 $
b101 '
b1111 #
b1111 &
b1 "
b1 %
