rtl/alu.sv
module alu (
    input logic [7:0] A, 
    input logic [7:0] B, 
    input logic [2:0] operation,
    output logic [7:0] result
); 
    always_comb 
        begin
            case(operation)
                3'b000: result = A + B; //ADD
                3'b001: result = A - B; //SUB
                3'b010: result = A & B; //AND
                3'b011: result = A | B; //OR
                3'b100: result = A ^ B; //XOR
                3'b101: result = A << B[2:0]; //SLL
                3'b110: result = A >> B[2:0]; //SRL
                3'b111: result = A == B; //Comparison
                default: result = 8'b00000000;
            endcase
        end 
endmodule

testbench/tb_alu.sv
module tb_alu;
    logic [7:0] A;
    logic [7:0] B;
    logic [2:0] operation;
    logic [7:0] result; 

    alu dut(
        .A(A),
        .B(B), 
        .operation(operation), 
        .result(result)
    ); 
    initial begin
        $dumpfile("alu_wave.vcd");
        $dumpvars(0, tb_alu);
        
        // Test Case 1: A = 3, B = 5, operation = 000 (Addition)
        A = 8'd3; 
        B = 8'd5; 
        operation = 3'b000; 
        #10; 
        if (result == 8'd8)
            $display("Test Case 1 Passed: Add %d + %d = %d", A, B, result);
        else
            $error("Test Case 1 Failed: Add %d + %d, expected 8, got %d", A, B, result);

         //Test Case 2: A = 3, B = 5, operation = 001 (Subtraction)
        A = 8'd3;
        B = 8'd5; 
        operation = 3'b001;
        #10;
        if (result == 8'd254) // 3 - 5 = -2 in 8-bit unsigned is 254
            $display("Test Case 2 Passed: Sub %d - %d = %d", A, B, result);
        else
            $error("Test Case 2 Failed: Sub %d - %d, expected 254, got %d", A, B, result);
        
        //Test Case 3: A = 3, B = 5, operation = 010 (AND)
        A = 8'd3;
        B = 8'd5; 
        operation = 3'b010;
        #10;
        if (result == 8'd1) // 3 & 5 = 1
            $display("Test Case 3 Passed: AND %d & %d = %d", A, B, result);
        else
            $error("Test Case 3 Failed: AND %d & %d, expected 1, got %d", A, B, result);

         //Test Case 4: A = 3, B = 5, operation = 011 (OR)
        A = 8'd3;
        B = 8'd5; 
        operation = 3'b011;
        #10;
        if (result == 8'd7) // 3 | 5 = 7
            $display("Test Case 4 Passed: OR %d | %d = %d", A, B, result);
        else 
            $error("Test Case 4 Failed: OR %d | %d, expected 7, got %d", A, B, result); 

         //Test Case 5: A = 3, B = 5, operation = 100 (XOR)
        A = 8'd3;
        B = 8'd5; 
        operation = 3'b100;
        #10;
        if (result == 8'd12) // 3 ^ 5 = 12
            $display("Test Case 5 Passed: XOR %d ^ %d = %d", A, B, result); 
        else
            $error("Test Case 5 Failed: XOR %d ^ %d, expected 12, got %d", A, B, result); 

         //Test Case 6: A = 3, B = 5, operation = 101 (SLL)
        A = 8'd3;
        B = 8'd5; 
        operation = 3'b101;
        #10;
        if (result == 8'd96) // 3 << 5 = 96
            $display("Test Case 6 Passed: SLL %d << %d = %d", A, B, result);
        else
            $error("Test Case 6 Failed: SLL %d << %d, expected 96, got %d", A, B, result);

         //Test Case 7: A = 3, B = 5, operation = 110 (SRL)
        A = 8'd3;
        B = 8'd5; 
        operation = 3'b110;
        #10;
        if (result == 8'd0) // 3 >> 5 = 0
            $display("Test Case 7 Passed: SRL %d >> %d = %d", A, B, result);
        else
            $error("Test Case 7 Failed: SRL %d >> %d, expected 0, got %d", A, B, result);

         //Test Case 8: A = 5, B = 5, operation = 111 (Comparison)
        A = 8'd5;
        B = 8'd5; 
        operation = 3'b111;
        #10;
        if (result == 8'd1) // 5 == 5 = 1
            $display("Test Case 8 Passed: Comparison %d == %d = %d", A, B, result);
        else
            $error("Test Case 8 Failed: Comparison %d == %d, expected 1, got %d", A, B, result);
    end
endmodule

alu_wave.vcd
$date
	Wed Aug 26 14:43:10 2026
$end
$version
	Icarus Verilog
$end
$timescale
	1s
$end
$scope module tb_alu $end
$var wire 8 ! result [7:0] $end
$var reg 8 " A [7:0] $end
$var reg 8 # B [7:0] $end
$var reg 3 $ operation [2:0] $end
$scope module dut $end
$var wire 8 % A [7:0] $end
$var wire 8 & B [7:0] $end
$var wire 3 ' operation [2:0] $end
$var reg 8 ( result [7:0] $end
$upscope $end
$upscope $end
$enddefinitions $end
$comment Show the parameter values. $end
$dumpall
$end
#0
$dumpvars
b1000 (
b0 '
b101 &
b11 %
b0 $
b101 #
b11 "
b1000 !
$end
#10
b11111110 !
b11111110 (
b1 $
b1 '
#20
b1 !
b1 (
b10 $
b10 '
#30
b111 !
b111 (
b11 $
b11 '
#40
b110 !
b110 (
b100 $
b100 '
#50
b1100000 !
b1100000 (
b101 $
b101 '
#60
b0 !
b0 (
b110 $
b110 '
#70
b1 !
b1 (
b111 $
b111 '
b101 "
b101 %
